setup.py
cldict/__init__.py
cldict/cmdln.py
cldict/dictcn.py
cldict.egg-info/PKG-INFO
cldict.egg-info/SOURCES.txt
cldict.egg-info/dependency_links.txt
cldict.egg-info/entry_points.txt
cldict.egg-info/requires.txt
cldict.egg-info/top_level.txt
tests/__init__.py
tests/test_dictcn.py