Metadata-Version: 1.0
Name: cldict
Version: 0.1.2
Summary: Command-line English-Chinese Dictionary
Home-page: https://github.com/zhuzhuor/cldict/
Author: Bo Zhu
Author-email: UNKNOWN
License: MIT
Platform: UNKNOWN
